{"page1layer1p1":[{"start":0,"end":0},{"start":26,"end":26}],"page1layer1p2":[{"start":0,"end":0},{"start":59,"end":59}],"page1layer1p3":[{"start":0,"end":0},{"start":83,"end":83}],"page1layer1p4":[{"start":0,"end":0},{"start":82,"end":82}],"page1layer1p5":[{"start":0,"end":0},{"start":62,"end":62}],"page1layer1p6":[{"start":0,"end":0},{"start":85,"end":85}],"page1layer1p7":[{"start":0,"end":0},{"start":75,"end":75}],"page1layer1p8":[{"start":0,"end":0},{"start":9,"end":9}],"page1layer1p9":[{"start":0,"end":0},{"start":971,"end":971}],"page1layer1p10":[{"start":0,"end":0},{"start":110,"end":110}],"page1layer1p11":[{"start":0,"end":0},{"start":60,"end":60}],"page1layer1p12":[{"start":0,"end":0},{"start":13,"end":13}],"page1layer1p13":[{"start":0,"end":0},{"start":275,"end":275}],"page1layer1p14":[{"start":0,"end":0},{"start":222,"end":222}],"page1layer1p15":[{"start":0,"end":0},{"start":616,"end":616}],"page1layer1p16":[{"start":0,"end":0},{"start":864,"end":864}],"page1layer1p17":[{"start":0,"end":0},{"start":846,"end":846}],"page1layer1p18":[{"start":0,"end":0},{"start":541,"end":541}],"page2layer1p1":[{"start":0,"end":0},{"start":99,"end":99}],"page2layer1p2":[{"start":0,"end":0},{"start":186,"end":186}],"page2layer1p3":[{"start":32,"end":32},{"start":231,"end":231}],"page2layer1p4":[{"start":33,"end":33},{"start":228,"end":228}],"page2layer1p5":[{"start":0,"end":0},{"start":588,"end":588}],"page2layer1p6":[{"start":0,"end":0},{"start":11,"end":11}],"page2layer1p7":[{"start":0,"end":0},{"start":1217,"end":1217}],"page2layer1p8":[{"start":0,"end":0},{"start":343,"end":343}],"page2layer1p9":[{"start":0,"end":0},{"start":745,"end":745}],"page2layer1p10":[{"start":0,"end":0},{"start":547,"end":547}],"page2layer1p11":[{"start":0,"end":0},{"start":14,"end":14}],"page2layer1p12":[{"start":0,"end":0},{"start":384,"end":384}],"page2layer1p13":[{"start":0,"end":0},{"start":1012,"end":1012}],"page2layer1p14":[{"start":0,"end":0},{"start":276,"end":276}],"page3layer1p1":[{"start":0,"end":0},{"start":243,"end":243}],"page3layer1p2":[{"start":0,"end":0},{"start":424,"end":424}],"page3layer1p3":[{"start":0,"end":0},{"start":614,"end":614}],"page3layer1p4":[{"start":0,"end":0},{"start":30,"end":30}],"page3layer1p5":[{"start":0,"end":0},{"start":261,"end":261}],"page3layer1p6":[{"start":0,"end":0},{"start":641,"end":641}],"page3layer1p7":[{"start":0,"end":0},{"start":62,"end":62}],"page3layer1p8":[{"start":0,"end":0},{"start":541,"end":541}],"page3layer1p9":[{"start":0,"end":0},{"start":40,"end":40}],"page3layer1p10":[{"start":0,"end":0},{"start":553,"end":553}],"page3layer1p11":[{"start":0,"end":0},{"start":711,"end":711}],"page3layer1p12":[{"start":0,"end":0},{"start":26,"end":26}],"page3layer1p13":[{"start":0,"end":0},{"start":748,"end":748}],"page3layer1p14":[{"start":0,"end":0},{"start":58,"end":58}],"page3layer1p15":[{"start":0,"end":0},{"start":167,"end":167}],"page4layer1p1":[{"start":0,"end":0},{"start":745,"end":745}],"page4layer1p2":[{"start":0,"end":0},{"start":23,"end":23}],"page4layer1p3":[{"start":0,"end":0},{"start":902,"end":902}],"page4layer1p4":[{"start":0,"end":0},{"start":105,"end":105}],"page4layer1p5":[{"start":0,"end":0},{"start":713,"end":713}],"page4layer1p6":[{"start":0,"end":0},{"start":10,"end":10}],"page4layer1p7":[{"start":0,"end":0},{"start":536,"end":536}],"page4layer1p8":[{"start":0,"end":0},{"start":800,"end":800}],"page4layer1p9":[{"start":0,"end":0},{"start":913,"end":913}],"page5layer1p1":[{"start":0,"end":0},{"start":1705,"end":1705}],"page5layer1p2":[{"start":0,"end":0},{"start":14,"end":14}],"page5layer1p3":[{"start":0,"end":0},{"start":641,"end":641}],"page5layer1p4":[{"start":0,"end":0},{"start":35,"end":35}],"page5layer1p5":[{"start":0,"end":0},{"start":414,"end":414}],"page5layer1p6":[{"start":0,"end":0},{"start":9,"end":9}],"page5layer1p7":[{"start":0,"end":0},{"start":106,"end":106}],"page5layer1p8":[{"start":0,"end":0},{"start":625,"end":625}],"page5layer1p9":[{"start":0,"end":0},{"start":836,"end":836}],"page5layer1p10":[{"start":0,"end":0},{"start":622,"end":622}],"page5layer1p11":[{"start":0,"end":0},{"start":849,"end":849}],"page5layer1p12":[{"start":0,"end":0},{"start":16,"end":16}],"page5layer1p13":[{"start":0,"end":0},{"start":53,"end":53}],"page6layer1p1":[{"start":0,"end":0},{"start":387,"end":387}],"page6layer1p2":[{"start":0,"end":0},{"start":423,"end":423}],"page6layer1p3":[{"start":0,"end":0},{"start":1101,"end":1101}],"page6layer1p4":[{"start":0,"end":0},{"start":10,"end":10}],"page6layer1p5":[{"start":0,"end":0},{"start":711,"end":711}],"page6layer1p6":[{"start":0,"end":0},{"start":316,"end":316}],"page6layer1p7":[{"start":0,"end":0},{"start":301,"end":301}],"page6layer1p8":[{"start":0,"end":0},{"start":1165,"end":1165}],"page6layer1p9":[{"start":0,"end":0},{"start":20,"end":20}],"page6layer1p10":[{"start":0,"end":0},{"start":366,"end":366}],"page6layer1p11":[{"start":0,"end":0},{"start":713,"end":713}],"page6layer1p12":[{"start":0,"end":0},{"start":325,"end":325}],"page7layer1p1":[{"start":0,"end":0},{"start":106,"end":106}],"page7layer1p2":[{"start":0,"end":0},{"start":804,"end":804}],"page7layer1p3":[{"start":0,"end":0},{"start":26,"end":26}],"page7layer1p4":[{"start":0,"end":0},{"start":365,"end":365}],"page7layer1p5":[{"start":0,"end":0},{"start":558,"end":558}],"page7layer1p6":[{"start":0,"end":0},{"start":225,"end":225}],"page7layer1p7":[{"start":0,"end":0},{"start":481,"end":481}],"page7layer1p8":[{"start":0,"end":0},{"start":16,"end":16}],"page7layer1p9":[{"start":0,"end":0},{"start":336,"end":336}],"page7layer1p10":[{"start":0,"end":0},{"start":969,"end":969}],"page7layer1p11":[{"start":0,"end":0},{"start":500,"end":500}],"page7layer1p12":[{"start":0,"end":0},{"start":852,"end":852}],"page7layer1p13":[{"start":0,"end":0},{"start":533,"end":533}],"page7layer1p14":[{"start":0,"end":0},{"start":171,"end":171}],"page8layer1p1":[{"start":0,"end":0},{"start":270,"end":270}],"page8layer1p2":[{"start":0,"end":0},{"start":330,"end":330}],"page8layer1p3":[{"start":0,"end":0},{"start":32,"end":32}],"page8layer1p4":[{"start":0,"end":0},{"start":732,"end":732}],"page8layer1p5":[{"start":0,"end":0},{"start":19,"end":19}],"page8layer1p6":[{"start":0,"end":0},{"start":424,"end":424}],"page8layer1p7":[{"start":0,"end":0},{"start":476,"end":476}],"page8layer1p8":[{"start":0,"end":0},{"start":558,"end":558}],"page8layer1p9":[{"start":0,"end":0},{"start":108,"end":108}],"page8layer1p10":[{"start":0,"end":0},{"start":19,"end":19}],"page8layer1p11":[{"start":0,"end":0},{"start":779,"end":779}],"page8layer1p12":[{"start":0,"end":0},{"start":390,"end":390}],"page8layer1p13":[{"start":0,"end":0},{"start":748,"end":748}],"page8layer1p14":[{"start":0,"end":0},{"start":24,"end":24}],"page8layer1p15":[{"start":0,"end":0},{"start":574,"end":574}],"page8layer1p16":[{"start":0,"end":0},{"start":231,"end":231}],"page9layer1p1":[{"start":0,"end":0},{"start":543,"end":543}],"page9layer1p2":[{"start":0,"end":0},{"start":1346,"end":1346}],"page9layer1p3":[{"start":0,"end":0},{"start":292,"end":292}],"page9layer1p4":[{"start":0,"end":0},{"start":28,"end":28}],"page9layer1p5":[{"start":0,"end":0},{"start":400,"end":400}],"page9layer1p6":[{"start":0,"end":0},{"start":11,"end":11}],"page9layer1p7":[{"start":0,"end":0},{"start":344,"end":344}],"page9layer1p8":[{"start":0,"end":0},{"start":230,"end":230}],"page9layer1p9":[{"start":0,"end":0},{"start":457,"end":457}],"page9layer1p10":[{"start":0,"end":0},{"start":451,"end":451}],"page9layer1p11":[{"start":0,"end":0},{"start":611,"end":611}],"page9layer1p12":[{"start":0,"end":0},{"start":840,"end":840}],"page9layer1p13":[{"start":0,"end":0},{"start":27,"end":27}],"page9layer1p14":[{"start":0,"end":0},{"start":411,"end":411}],"page10layer1p1":[{"start":0,"end":0},{"start":615,"end":615}],"page10layer1p2":[{"start":0,"end":0},{"start":692,"end":692}],"page10layer1p3":[{"start":0,"end":0},{"start":554,"end":554}],"page10layer1p4":[{"start":0,"end":0},{"start":559,"end":559}],"page10layer1p5":[{"start":0,"end":0},{"start":380,"end":380}],"page10layer1p6":[{"start":0,"end":0},{"start":23,"end":23}],"page10layer1p7":[{"start":0,"end":0},{"start":111,"end":111}],"page10layer1p8":[{"start":0,"end":0},{"start":574,"end":574}],"page10layer1p9":[{"start":0,"end":0},{"start":334,"end":334}],"page10layer1p10":[{"start":0,"end":0},{"start":768,"end":768}],"page10layer1p11":[{"start":0,"end":0},{"start":520,"end":520}],"page10layer1p12":[{"start":0,"end":0},{"start":651,"end":651}],"page11layer1p1":[{"start":0,"end":0},{"start":105,"end":105}],"page11layer1p2":[{"start":0,"end":0},{"start":11,"end":11}],"page11layer1p3":[{"start":0,"end":0},{"start":378,"end":378}],"page11layer1p4":[{"start":0,"end":0},{"start":22,"end":22}],"page11layer1p5":[{"start":0,"end":0},{"start":48,"end":48}],"page11layer1p6":[{"start":0,"end":0},{"start":632,"end":632}],"page11layer1p7":[{"start":0,"end":0},{"start":1024,"end":1024}],"page11layer1p8":[{"start":0,"end":0},{"start":49,"end":49}],"page11layer1p9":[{"start":0,"end":0},{"start":107,"end":107}],"page11layer1p10":[{"start":0,"end":0},{"start":625,"end":625}],"page11layer1p11":[{"start":0,"end":0},{"start":257,"end":257}],"page11layer1p12":[{"start":0,"end":0},{"start":616,"end":616}],"page11layer1p13":[{"start":0,"end":0},{"start":1095,"end":1095}],"page11layer1p14":[{"start":0,"end":0},{"start":20,"end":20}],"page11layer1p15":[{"start":0,"end":0},{"start":115,"end":115}],"page11layer1p16":[{"start":0,"end":0},{"start":962,"end":962}],"page12layer1p1":[{"start":0,"end":0},{"start":987,"end":987}],"page12layer1p2":[{"start":0,"end":0},{"start":11,"end":11}],"page12layer1p3":[{"start":0,"end":0},{"start":390,"end":390}],"page12layer1p4":[{"start":0,"end":0},{"start":849,"end":849}],"page12layer1p5":[{"start":0,"end":0},{"start":696,"end":696}],"page12layer1p6":[{"start":0,"end":0},{"start":62,"end":62}],"page12layer1p7":[{"start":0,"end":0},{"start":988,"end":988}],"page12layer1p8":[{"start":0,"end":0},{"start":17,"end":17}],"page12layer1p9":[{"start":0,"end":0},{"start":403,"end":403}],"page12layer1p10":[{"start":0,"end":0},{"start":380,"end":380}],"page12layer1p11":[{"start":0,"end":0},{"start":180,"end":180}],"page12layer1p12":[{"start":0,"end":0},{"start":11,"end":11}],"page12layer1p13":[{"start":0,"end":0},{"start":151,"end":151}],"page12layer1p14":[{"start":0,"end":0},{"start":166,"end":166}],"page12layer1p15":[{"start":0,"end":0},{"start":172,"end":172}],"page12layer1p16":[{"start":0,"end":0},{"start":89,"end":89}],"page13layer1p1":[{"start":0,"end":0},{"start":95,"end":95}],"page13layer1p2":[{"start":0,"end":0},{"start":213,"end":213}],"page13layer1p3":[{"start":0,"end":0},{"start":161,"end":161}],"page13layer1p4":[{"start":0,"end":0},{"start":161,"end":161}],"page13layer1p5":[{"start":0,"end":0},{"start":112,"end":112}],"page13layer1p6":[{"start":0,"end":0},{"start":158,"end":158}],"page13layer1p7":[{"start":0,"end":0},{"start":153,"end":153}],"page13layer1p8":[{"start":0,"end":0},{"start":132,"end":132}],"page13layer1p9":[{"start":0,"end":0},{"start":114,"end":114}],"page13layer1p10":[{"start":0,"end":0},{"start":155,"end":155}],"page13layer1p11":[{"start":0,"end":0},{"start":164,"end":164}],"page13layer1p12":[{"start":0,"end":0},{"start":125,"end":125}],"page13layer1p13":[{"start":0,"end":0},{"start":271,"end":271}],"page13layer1p14":[{"start":0,"end":0},{"start":123,"end":123}],"page13layer1p15":[{"start":0,"end":0},{"start":142,"end":142}],"page13layer1p16":[{"start":0,"end":0},{"start":172,"end":172}],"page13layer1p17":[{"start":0,"end":0},{"start":179,"end":179}],"page13layer1p18":[{"start":0,"end":0},{"start":147,"end":147}],"page13layer1p19":[{"start":0,"end":0},{"start":174,"end":174}],"page13layer1p20":[{"start":0,"end":0},{"start":270,"end":270}],"page13layer1p21":[{"start":0,"end":0},{"start":237,"end":237}],"page13layer1p22":[{"start":0,"end":0},{"start":256,"end":256}],"page13layer1p23":[{"start":0,"end":0},{"start":140,"end":140}],"page13layer1p24":[{"start":0,"end":0},{"start":142,"end":142}],"page13layer1p25":[{"start":0,"end":0},{"start":92,"end":92}],"page13layer1p26":[{"start":0,"end":0},{"start":127,"end":127}],"page13layer1p27":[{"start":0,"end":0},{"start":73,"end":73}],"page13layer1p28":[{"start":0,"end":0},{"start":145,"end":145}],"page13layer1p29":[{"start":0,"end":0},{"start":113,"end":113}],"page13layer1p30":[{"start":0,"end":0},{"start":165,"end":165}],"page13layer1p31":[{"start":0,"end":0},{"start":117,"end":117}],"page13layer1p32":[{"start":0,"end":0},{"start":55,"end":55}],"page14layer1p1":[{"start":0,"end":0},{"start":200,"end":200}],"page14layer1p2":[{"start":0,"end":0},{"start":143,"end":143}],"page14layer1p3":[{"start":0,"end":0},{"start":160,"end":160}],"page14layer1p4":[{"start":0,"end":0},{"start":185,"end":185}],"page14layer1p5":[{"start":0,"end":0},{"start":159,"end":159}],"page14layer1p6":[{"start":0,"end":0},{"start":45,"end":45}],"page14layer1p7":[{"start":0,"end":0},{"start":73,"end":73}],"page14layer1p8":[{"start":0,"end":0},{"start":123,"end":123}],"page14layer1p9":[{"start":0,"end":0},{"start":245,"end":245}],"page14layer1p10":[{"start":0,"end":0},{"start":114,"end":114}],"page14layer1p11":[{"start":0,"end":0},{"start":145,"end":145}],"page14layer1p12":[{"start":0,"end":0},{"start":141,"end":141}],"page14layer1p13":[{"start":0,"end":0},{"start":198,"end":198}],"page14layer1p14":[{"start":0,"end":0},{"start":86,"end":86}],"page14layer1p15":[{"start":0,"end":0},{"start":136,"end":136}],"page14layer1p16":[{"start":0,"end":0},{"start":110,"end":110}],"page14layer1p17":[{"start":0,"end":0},{"start":139,"end":139}],"page14layer1p18":[{"start":0,"end":0},{"start":102,"end":102}],"page14layer1p19":[{"start":0,"end":0},{"start":150,"end":150}],"page14layer1p20":[{"start":0,"end":0},{"start":77,"end":77}],"page14layer1p21":[{"start":0,"end":0},{"start":121,"end":121}],"page14layer1p22":[{"start":0,"end":0},{"start":144,"end":144}],"page14layer1p23":[{"start":0,"end":0},{"start":162,"end":162}],"page14layer1p24":[{"start":0,"end":0},{"start":178,"end":178}],"page14layer1p25":[{"start":0,"end":0},{"start":136,"end":136}],"page14layer1p26":[{"start":0,"end":0},{"start":53,"end":53}],"page14layer1p27":[{"start":0,"end":0},{"start":110,"end":110}],"page14layer1p28":[{"start":0,"end":0},{"start":158,"end":158}],"page14layer1p29":[{"start":0,"end":0},{"start":159,"end":159}],"page14layer1p30":[{"start":0,"end":0},{"start":118,"end":118}],"page14layer1p31":[{"start":0,"end":0},{"start":168,"end":168}],"page14layer1p32":[{"start":0,"end":0},{"start":148,"end":148}],"page14layer1p33":[{"start":0,"end":0},{"start":139,"end":139}],"page14layer1p34":[{"start":0,"end":0},{"start":152,"end":152}],"page14layer1p35":[{"start":0,"end":0},{"start":141,"end":141}],"page14layer1p36":[{"start":0,"end":0},{"start":110,"end":110}],"page14layer1p37":[{"start":0,"end":0},{"start":52,"end":52}],"page15layer1p1":[{"start":0,"end":0},{"start":153,"end":153}],"page15layer1p2":[{"start":0,"end":0},{"start":202,"end":202}],"page15layer1p3":[{"start":0,"end":0},{"start":131,"end":131}],"page15layer1p4":[{"start":0,"end":0},{"start":242,"end":242}],"page15layer1p5":[{"start":0,"end":0},{"start":199,"end":199}],"page15layer1p6":[{"start":0,"end":0},{"start":213,"end":213}],"page15layer1p7":[{"start":0,"end":0},{"start":86,"end":86}],"page15layer1p8":[{"start":0,"end":0},{"start":180,"end":180}],"page15layer1p9":[{"start":0,"end":0},{"start":205,"end":205}],"page15layer1p10":[{"start":0,"end":0},{"start":243,"end":243}],"page15layer1p11":[{"start":0,"end":0},{"start":97,"end":97}],"page15layer1p12":[{"start":0,"end":0},{"start":269,"end":269}],"page15layer1p13":[{"start":0,"end":0},{"start":157,"end":157}],"page15layer1p14":[{"start":0,"end":0},{"start":149,"end":149}],"page15layer1p15":[{"start":0,"end":0},{"start":244,"end":244}],"page15layer1p16":[{"start":0,"end":0},{"start":191,"end":191}],"page15layer1p17":[{"start":0,"end":0},{"start":221,"end":221}],"page15layer1p18":[{"start":0,"end":0},{"start":90,"end":90}],"page15layer1p19":[{"start":0,"end":0},{"start":130,"end":130}],"page15layer1p20":[{"start":0,"end":0},{"start":144,"end":144}],"page15layer1p21":[{"start":0,"end":0},{"start":152,"end":152}],"page15layer1p22":[{"start":0,"end":0},{"start":55,"end":55}],"page15layer1p23":[{"start":0,"end":0},{"start":123,"end":123}],"page15layer1p24":[{"start":0,"end":0},{"start":119,"end":119}],"page15layer1p25":[{"start":0,"end":0},{"start":125,"end":125}],"page15layer1p26":[{"start":0,"end":0},{"start":104,"end":104}],"page15layer1p27":[{"start":0,"end":0},{"start":117,"end":117}],"page15layer1p28":[{"start":0,"end":0},{"start":181,"end":181}],"page15layer1p29":[{"start":0,"end":0},{"start":130,"end":130}],"page15layer1p30":[{"start":0,"end":0},{"start":189,"end":189}],"page15layer1p31":[{"start":0,"end":0},{"start":197,"end":197}],"page15layer1p32":[{"start":0,"end":0},{"start":49,"end":49}],"page16layer1p1":[{"start":0,"end":0},{"start":97,"end":97}],"page16layer1p2":[{"start":0,"end":0},{"start":149,"end":149}],"page16layer1p3":[{"start":0,"end":0},{"start":188,"end":188}],"page16layer1p4":[{"start":0,"end":0},{"start":120,"end":120}],"page16layer1p5":[{"start":0,"end":0},{"start":158,"end":158}],"page16layer1p6":[{"start":0,"end":0},{"start":223,"end":223}],"page16layer1p7":[{"start":0,"end":0},{"start":103,"end":103}],"page16layer1p8":[{"start":0,"end":0},{"start":175,"end":175}],"page16layer1p9":[{"start":0,"end":0},{"start":226,"end":226}],"page16layer1p10":[{"start":0,"end":0},{"start":188,"end":188}],"page16layer1p11":[{"start":0,"end":0},{"start":117,"end":117}],"page16layer1p12":[{"start":0,"end":0},{"start":183,"end":183}],"page16layer1p13":[{"start":0,"end":0},{"start":293,"end":293}],"page16layer1p14":[{"start":0,"end":0},{"start":181,"end":181}],"page16layer1p15":[{"start":0,"end":0},{"start":158,"end":158}],"page16layer1p16":[{"start":0,"end":0},{"start":161,"end":161}],"page16layer1p17":[{"start":0,"end":0},{"start":205,"end":205}],"page16layer1p18":[{"start":0,"end":0},{"start":152,"end":152}],"page16layer1p19":[{"start":0,"end":0},{"start":240,"end":240}],"page16layer1p20":[{"start":0,"end":0},{"start":91,"end":91}],"page16layer1p21":[{"start":0,"end":0},{"start":117,"end":117}],"page16layer1p22":[{"start":0,"end":0},{"start":155,"end":155}],"page16layer1p23":[{"start":0,"end":0},{"start":100,"end":100}],"page16layer1p24":[{"start":0,"end":0},{"start":134,"end":134}],"page16layer1p25":[{"start":0,"end":0},{"start":190,"end":190}],"page16layer1p26":[{"start":0,"end":0},{"start":219,"end":219}],"page16layer1p27":[{"start":0,"end":0},{"start":177,"end":177}],"page16layer1p28":[{"start":0,"end":0},{"start":118,"end":118}],"page16layer1p29":[{"start":0,"end":0},{"start":134,"end":134}],"page16layer1p30":[{"start":0,"end":0},{"start":135,"end":135}],"page17layer1p1":[{"start":0,"end":0},{"start":84,"end":84}],"page17layer1p2":[{"start":0,"end":0},{"start":172,"end":172}],"page17layer1p3":[{"start":0,"end":0},{"start":110,"end":110}],"page17layer1p4":[{"start":0,"end":0},{"start":71,"end":71}],"page17layer1p5":[{"start":0,"end":0},{"start":39,"end":39}],"page17layer1p6":[{"start":0,"end":0},{"start":135,"end":135}],"page17layer1p7":[{"start":0,"end":0},{"start":72,"end":72}],"page17layer1p8":[{"start":0,"end":0},{"start":183,"end":183}],"page17layer1p9":[{"start":0,"end":0},{"start":97,"end":97}],"page17layer1p10":[{"start":0,"end":0},{"start":154,"end":154}],"page17layer1p11":[{"start":0,"end":0},{"start":160,"end":160}],"page17layer1p12":[{"start":0,"end":0},{"start":227,"end":227}],"page17layer1p13":[{"start":0,"end":0},{"start":132,"end":132}],"page17layer1p14":[{"start":0,"end":0},{"start":208,"end":208}],"page17layer1p15":[{"start":0,"end":0},{"start":157,"end":157}],"page17layer1p16":[{"start":0,"end":0},{"start":137,"end":137}],"page17layer1p17":[{"start":0,"end":0},{"start":195,"end":195}],"page17layer1p18":[{"start":0,"end":0},{"start":263,"end":263}],"page17layer1p19":[{"start":0,"end":0},{"start":127,"end":127}],"page17layer1p20":[{"start":0,"end":0},{"start":190,"end":190}],"page17layer1p21":[{"start":0,"end":0},{"start":138,"end":138}],"page17layer1p22":[{"start":0,"end":0},{"start":154,"end":154}],"page17layer1p23":[{"start":0,"end":0},{"start":211,"end":211}],"page17layer1p24":[{"start":0,"end":0},{"start":203,"end":203}],"page17layer1p25":[{"start":0,"end":0},{"start":120,"end":120}],"page17layer1p26":[{"start":0,"end":0},{"start":106,"end":106}]}