{
	"p1":[{"start":0,"end":0,"style":"highlight"},{"start":673,"end":673,"style":"highlight"}],
	"p2":[{"start":0,"end":0,"style":"highlight"},{"start":508,"end":508,"style":"highlight"}],
	"p3":[{"start":0,"end":0,"style":"highlight"},{"start":422,"end":422,"style":"highlight"}],
	"p4":[{"start":0,"end":0,"style":"highlight"},{"start":183,"end":183,"style":"highlight"}],
	"p5":[{"start":0,"end":0,"style":"highlight"},{"start":274,"end":274,"style":"highlight"}],
	"p6":[{"start":0,"end":0,"style":"highlight"},{"start":495,"end":495,"style":"highlight"}],
	"p7":[{"start":0,"end":0,"style":"highlight"},{"start":873,"end":873,"style":"highlight"}],
}